LICENSE
MANIFEST.in
README.rst
requirements.txt
setup.cfg
setup.py
versioneer.py
docs/Makefile
docs/make.bat
docs/source/conf.py
docs/source/contactus.rst
docs/source/examples.rst
docs/source/index.rst
docs/source/ingest.rst
docs/source/install.rst
docs/source/releases.rst
fsharadar/__init__.py
fsharadar/_version.py
fsharadar/adjustments.py
fsharadar/asset_metadata.py
fsharadar/bcolz_reader_float64.py
fsharadar/bcolz_writer_float64.py
fsharadar/cython_read_float64.pyx
fsharadar/data_portal.py
fsharadar/db_access.py
fsharadar/db_schema.py
fsharadar/defs.py
fsharadar/ingest.py
fsharadar/load.py
fsharadar/pipe_loader.py
fsharadar/read.py
fsharadar/universe.py
fsharadar/utils.py
fsharadar.egg-info/PKG-INFO
fsharadar.egg-info/SOURCES.txt
fsharadar.egg-info/dependency_links.txt
fsharadar.egg-info/entry_points.txt
fsharadar.egg-info/requires.txt
fsharadar.egg-info/top_level.txt
fsharadar/daily/__init__.py
fsharadar/daily/ingest.py
fsharadar/daily/load.py
fsharadar/daily/meta.py
fsharadar/sep/__init__.py
fsharadar/sep/get_pricing.py
fsharadar/sep/ingest.py
fsharadar/sep/load.py
fsharadar/sep/meta.py
fsharadar/sfp/__init__.py
fsharadar/sfp/get_pricing.py
fsharadar/sfp/ingest.py
fsharadar/sfp/load.py
fsharadar/sfp/meta.py