Metadata-Version: 1.2
Name: fsharadar
Version: 0.3.0
Summary: Flounder interface of the Zipline platform to the Sharadar data.
Home-page: https://flounderteam.github.io/fsharadar/
Author: Flounder Team
Author-email: flounderhost@gmail.com
License: MIT
Platform: UNKNOWN
Classifier: Development Status :: 3 - Alpha
Classifier: Natural Language :: English
Classifier: Programming Language :: Python :: 3
Requires-Python: >=3.6
